logging_monitor/main.py
logging_monitor-0.0.1.dist-info/LICENSE
logging_monitor-0.0.1.dist-info/METADATA
logging_monitor-0.0.1.dist-info/WHEEL
logging_monitor-0.0.1.dist-info/RECORD
