Metadata-Version: 2.1
Name: logging-monitor
Version: 0.0.1
Summary: 
Author: DZIUREWICZ Piotr
Author-email: dziurewiczpiotr@gmail.com
Requires-Python: >=3.8,<4.0
Classifier: Programming Language :: Python :: 3
Classifier: Programming Language :: Python :: 3.8
Classifier: Programming Language :: Python :: 3.9
Classifier: Programming Language :: Python :: 3.10
Classifier: Programming Language :: Python :: 3.11
Requires-Dist: fastapi (>=0.95.2,<0.96.0)
Requires-Dist: uvicorn (>=0.22.0,<0.23.0)
